ton_address_converter-0.1.0.dist-info/METADATA
ton_address_converter-0.1.0.dist-info/WHEEL
ton_address_converter-0.1.0.dist-info/licenses/LICENSE
ton_address_converter/__init__.py
ton_address_converter/__init__.pyi
ton_address_converter/py.typed
ton_address_converter/ton_address_converter.cpython-311-x86_64-linux-gnu.so
ton_address_converter-0.1.0.dist-info/RECORD
